openrazer/__init__.py
openrazer-0.0.1.dist-info/METADATA
openrazer-0.0.1.dist-info/WHEEL
openrazer-0.0.1.dist-info/top_level.txt
openrazer-0.0.1.dist-info/RECORD
