Metadata-Version: 2.1
Name: openrazer
Version: 0.0.1
Summary: Library for interacting with the OpenRazer daemon.
